<?xml version="1.0" encoding="UTF-8"?>
<npc name="An Old Smith" script="anoldsmith.lua" walkinterval="2000" floorchange="0" walkradius="3">
	<health now="100" max="100" />
	<look type="165"/>
	<parameters>
		<parameter key="message_greet" value="Welcome, |PLAYERNAME|."/>
		<parameter key="message_farewell" value="Good bye and come again."/>
        <parameter key="module_keywords" value="1" />
        <parameter key="keywords" value="job" />
		<parameter key="module_shop" value="1"/>
        <parameter key="keyword_reply1" value="I buy rare weapons and armor." />
		<parameter key="shop_sellable" value="samurai sword,5226,30000;scarab shield,2540,2000;dragon shield,2516,5000;knight armor,2476,5000;knight legs,2477,5000;amber staff,5212,8000;ancient amulet,2142,20000;beastslayer axe,3962,1500;blue robe,2656,10000;beholder shield,2518,1200;boots of haste,2195,30000;broadsword,2413,500;butcher's axe,5201,18000;crown armor,2487,12000;crown helmet,2491,2500;crown legs,2488,12000;crown shield,2519,8000;crusader helmet,2497,6000;dragon lance,2414,9000;fire axe,2432,8000;fire sword,2392,4000;glorious axe,5203,3000;guardian shield,2515,2000;ice rapier,2396,1000;noble armor,2486,900;obsidian lance,2425,500;phoenix shield,2539,16000;queen's sceptre,5027,20000;royal helmet,2498,30000;spike sword,2383,1000;thaian sword,5223,16000;war hammer,2391,1200;blessed sceptre,5029,40000;bone shield,2541,80;bonelord helmet,3972,7500;castle shield,2535,5000;arbalest,5232,40000;dragon scale boots,3982,7000;crystal mace,2445,12000;crystal necklace,2125,400;crystal ring,2124,250;crystal sword,5222,6000;daramian mace,2439,110;daramian waraxe,2440,1000;dark shield,2521,400;death ring,5312,1000;demon shield,2520,30000;demonbone amulet,2136,32000;devil helmet,2462,1000;diamond sceptre,5211,3000;divine plate,5709,55000;djinn blade,2451,15000;dragon scale mail,2492,40000;relic sword,5225,15000;dreaded cleaver,5200,10000;dwarven armor,2503,30000;elvish bow,5707,40000;emerald bangle,2127,800;epee,2438,8000;pirate boots,5328,2000;furry club,5210,1000;glacier amulet,5192,1500;glacier kilt,5190,11000;glacier mask,5188,2500;glacier robe,5189,11000;glacier shoes,5191,2500;gold ring,2179,8000;golden armor,2466,20000;golden legs,2470,30000;guardian halberd,2427,11000;hammer of wrath,2444,30000;heavy mace,2452,50000;heavy machete,2442,90;heroic axe,5204,30000;jade hammer,5216,25000;leopard armor,3968,1000;lightning boots,5187,2500;lightning headband,5184,2500;lightning legs,5186,11000;lightning pendant,5024,1500;lightning robe,5185,11000;magic plate armor,2472,90000;magma amulet,5195,1500;magma boots,5194,2500;magma coat,5025,11000;magma legs,5026,11000;magma monocle,5193,2500;mastermind shield,2514,50000;medusa shield,2536,9000;mystic blade,5227,30000;naginata,2426,2000;noble axe,5199,10000;norse shield,5708,1500;pair of iron fists,5219,70000;paladin armor,5239,15000;samurai boots,2641,2000;pharaoh sword,2446,23000;platinum amulet,2171,2500;relic sword,5225,25000;ring of the sky,2123,30000;royal axe,5206,40000;ruby necklace,2133,2000;ruthless axe,5207,45000;sapphire hammer,5213,7000;scarab amulet,2135,200;scarab shield,2540,2000;silver brooch,2134,150;silver dagger,2402,500;skull helmet,5178,40000;steel boots,2645,30000;tempest shield,2542,35000;venom amulet,5183,1500;venom boots,5182,2500;venom hood,5179,2500;venom legs,5181,11000;venom mantle,5180,11000;the justice seeker,5229,40000;tortoise shield,5314,150;crystalline axe,5208,90000;war axe,2454,12000;wyvern fang,5221,1500;serpent sword,2409,1500;dark armor,2489,400;warrior helmet,2475,8000;dragon scale boots,3982,5000;tower shield,2528,8000;dark helmet,2490,250;strange helmet,2479,250;daramanian waraxe,2440,10000;knight axe,2430,1500;skull staff,2436,6000;focus cape,5234,5000;spirit cloak,5233,1000;giant sword,2393,17000;dragon hammer,2434,2000;rose shield,2527,7500;ancient shield,2532,1500;samurai armor,5238,30000;"/>
	</parameters>
</npc>